singular/__init__.py
singular/cli.py
singular/components.py
singular/core.py
singular/elements.py
singular/router.py
singular/utils.py
singular/static/css/base.css
singular/static/js/brython.js
singular/static/js/brython_stdlib.js
singular/static/js/htmx.min.js
singular/static/js/main.py
singular/static/js/singular.py
singular/static/js/__pycache__/singular.cpython-312.pyc
singular/templates/base.html
singular_framework-1.0.0.dist-info/METADATA
singular_framework-1.0.0.dist-info/WHEEL
singular_framework-1.0.0.dist-info/entry_points.txt
singular_framework-1.0.0.dist-info/top_level.txt
singular_framework-1.0.0.dist-info/RECORD
