Metadata-Version: 2.4
Name: singular-framework
Version: 1.0.0
Summary: Framework web da linha Singular
Author-email: Ricardo Kayoca <ricacayoca2rdo@gmail.com>
License: MIT
Classifier: Programming Language :: Python :: 3
Classifier: Programming Language :: Python :: 3 :: Only
Classifier: License :: OSI Approved :: MIT License
Classifier: Operating System :: OS Independent
Classifier: Framework :: Flask
Classifier: Environment :: Web Environment
Requires-Python: >=3.8
Requires-Dist: click
Requires-Dist: jinja2
Requires-Dist: werkzeug
Requires-Dist: watchdog
Requires-Dist: flask
